sphinxcontrib_pandoc_markdown-1.6.8-py3.6-nspkg.pth
sphinxcontrib/pandoc_markdown.py
sphinxcontrib/remove_caption_filter.py
sphinxcontrib_pandoc_markdown-1.6.8.dist-info/DESCRIPTION.rst
sphinxcontrib_pandoc_markdown-1.6.8.dist-info/METADATA
sphinxcontrib_pandoc_markdown-1.6.8.dist-info/RECORD
sphinxcontrib_pandoc_markdown-1.6.8.dist-info/WHEEL
sphinxcontrib_pandoc_markdown-1.6.8.dist-info/metadata.json
sphinxcontrib_pandoc_markdown-1.6.8.dist-info/namespace_packages.txt
sphinxcontrib_pandoc_markdown-1.6.8.dist-info/top_level.txt
