Metadata-Version: 2.0
Name: sphinxcontrib-pandoc-markdown
Version: 1.6.8
Summary: Yet another markdown processor for Sphinx
Home-page: https://github.com/pashango2/sphinxcontrib-pandoc-markdown/
Author: Toshiyuki Ishii
Author-email: pashango2@gmail.com
License: BSD
Platform: any
Classifier: Development Status :: 3 - Alpha
Classifier: Environment :: Console
Classifier: Framework :: Sphinx :: Extension
Classifier: Intended Audience :: Developers
Classifier: License :: OSI Approved :: BSD License
Classifier: Operating System :: OS Independent
Classifier: Programming Language :: Python
Classifier: Programming Language :: Python :: 2.7
Classifier: Programming Language :: Python :: 3.3
Classifier: Programming Language :: Python :: 3.4
Classifier: Programming Language :: Python :: 3.5
Classifier: Programming Language :: Python :: 3.6
Classifier: Topic :: Documentation
Classifier: Topic :: Documentation :: Sphinx
Classifier: Topic :: Utilities
Requires-Dist: Sphinx (>=0.6)
Requires-Dist: pandocfilters
